{
    "name": "Morning Ride",
    "distance": 66.0,
    "movingTime": 8677,
    "elevation": 260,
    "averageWatts": 150,
    "weightedAverageWatts": 153,
    "maxWatts": 547,
    "kilojoules": 1295,
    "deviceName": "Garmin Edge 540",
    "startDate": "2026-04-26T06:41:07Z",
    "sufferScore": 0,
    "summaryPolyline": "av_sCou{~UOPDTe@lA_Bi@aAfA}DoEiE{Bw@S]iBoAiAaI}DmAUmLFsAnBaPkHyEjD}BrAcEvAaHz@wCjA{AbAcBfBgBpC_ExLkDfEgBlAq\\rG_[nF{CjAyB|AuK`N_M~L}KpIsDxBgUpK{A|AOGe@uDc@RKZB`@n@xDQNoa@eI{NuDyx@k\\eG{CaEuCwQoQyCcCaCyA_EcB_MwCqyB_^aDq@sFkBkE_CmEkDc`A}{@iE{C}EyBiIcBqYgBaHImQXgFIsEo@sFuBaLbB?Y|BaHH{@sF}ImBkBeDyB}C{AgFsA{r@_LwDkAwCgByC_DwBmDmBwEuIqWgCuEsBgCcFkE}fAgx@_GkDoEeB{FkAaQgCcGsBcLeF{HkCcJeBmWeDuD_AiCkAeCoBoBoCqAkCkDsJsDyGyEgFeGoEkEgEaCwDmEaJgCeDyHyGom@ed@aEoCsDqBkf@sVyEqB}IwBeS{A_EaAuCoA_EoCu@{@gI}TmAuBu@gDoDqFeD_D_DoB}CoAgd@sUqIqD}[oLmF_CmCeB{AuAqEoFeG{I{CuDsFyEyAwFuA{CXyE[oDs@aCPcBz@oDLmAIs@cDwBcEuGaDqCORqLj@}IwBeCoA_AiA]uEsA}Aa@cAI}ArA{BHmBoCiDI?KjAIJc@{Am@i@s@CU`@MtAFd@dB~AIjDTn@rBf@b@pArA~APh@ZfE~@lA~AbAtKdClL_@nCpBnEbHjAbA`Bn@Dv@gApESlBp@xBb@nEe@tDfBnErAnF^b@zAt@rClCbMxPzCrDhB~AjBnAfGdC`a@bOxJtEp^bRTXXrAtDhCxBnBnCrDlCxF|Ax@zIxVjApAfCfBbClA`DbAdDd@nQtA|HnBpc@nTrPhJfi@va@hLhIhB`B~B~CtEnJjCxD`CdCxIzGvDbErC`FnEzLhAzBlCnDlCpBtBbAlD|@z[hE~HfBtG~BjK|EfH~BhQ`DrG`BdFtBjF~CvdAhv@zEjEbBxBzBnEnBtFzFxRx@lBrBjDbBdBxDjCbFlBjDt@nl@dJ~D|@vDdBzCjBfBzAdClCfEvFBXyBxGB\\tAInGiAjEvBzCx@jBVzENbPYzKNdXbBpDd@xCv@dF~BzCxBlbA~}@~ElDxDlBbErAbI|A~zBd^jFjAvCjA`E|BdX|VlFhDfF`Cxy@x\\vKtCfO|C~QzC~Aj@c@gDx@qA~UiL~H}EpGiFhLcLbCyCx@i@~F}HzAkAxBkArA[~w@{NjA{@e@cAjEcF`@AjAl@~BuIz@oBn@{@bDmC|BgAdHqAjDaAfF}BdDyBv@IvBp@|[fOlGxC\\^"
}